{"authorDailyContributionsMap":{"advaypakhale":[],"Mingyuan03":[],"Timothy-Ho0203":[],"DESU-CLUB":[{"date":"2025-02-23","commitResults":[{"hash":"d6e09a1a71c154edc0627bb05911f0f37080fd9c","isMergeCommit":false,"messageTitle":"Add markbind support","messageBody":"","fileTypesAndContributionMap":{"docs":{"insertions":1,"deletions":1}}}]}]},"authorFileTypeContributionMap":{"advaypakhale":{"docs":0,"functional-code":0,"test-code":0},"Mingyuan03":{"docs":0,"functional-code":0,"test-code":0},"Timothy-Ho0203":{"docs":0,"functional-code":0,"test-code":0},"DESU-CLUB":{"docs":1,"functional-code":0,"test-code":0}},"authorContributionVariance":{"advaypakhale":0.0,"Mingyuan03":0.0,"Timothy-Ho0203":0.0,"DESU-CLUB":0.88888884},"authorDisplayNameMap":{"advaypakhale":"CS2103T-T08-4 PAKH..ILIP","Mingyuan03":"CS2103T-T08-4 LU M..YUAN","Timothy-Ho0203":"CS2103T-T08-4 TIMO..F HO","DESU-CLUB":"CS2103T-T08-4 LOW ..RREN"}}
