{"authorDailyContributionsMap":{"dragonesejosh":[{"date":"2025-02-21","commitResults":[{"hash":"0f24b338855c2abe1fcc488c82972ab7e10cf25d","isMergeCommit":false,"messageTitle":"Update README.md","messageBody":"","fileTypesAndContributionMap":{"docs":{"insertions":2,"deletions":0}}}]},{"date":"2025-03-05","commitResults":[{"hash":"8374d0c937831b68d9353a1e2925fe26a3b462e5","isMergeCommit":false,"messageTitle":"Update AboutUs with photo","messageBody":"","fileTypesAndContributionMap":{"docs":{"insertions":3,"deletions":3}}},{"hash":"c67415c2fba236ff9cddc5971ac822529b8b13e4","isMergeCommit":true,"messageTitle":"Merge pull request #20 from gekjunxu/add-about-us","messageBody":"Update AboutUs for Jun Xu","fileTypesAndContributionMap":{}},{"hash":"8c3052aac6259c611eeda75f34decffb062da6f0","isMergeCommit":true,"messageTitle":"Merge pull request #21 from swatirajesh277/branch-update-aboutus","messageBody":"update about us with swati\u0027s photo","fileTypesAndContributionMap":{}},{"hash":"d31309cae49cd23482c2ea364451b4f65af730ad","isMergeCommit":true,"messageTitle":"Merge pull request #22 from ShiJianXi/branch-UpdateAboutUs-JianXi","messageBody":"Update AboutUs by JianXi","fileTypesAndContributionMap":{}},{"hash":"c79d97b04ac3595195444fa7806e99a625a248fd","isMergeCommit":true,"messageTitle":"Merge pull request #23 from dragonesejosh/v1.1-update-about-us","messageBody":"Update AboutUs with Joshua\u0027s photo","fileTypesAndContributionMap":{}},{"hash":"da5c58c2f1bf3f124df2960964fc648eae0b8e12","isMergeCommit":true,"messageTitle":"Merge pull request #24 from weiwong834/branch-Update-AboutUs","messageBody":"Update AboutUs with Wei Yin\u0027s Photo","fileTypesAndContributionMap":{}}]}],"weiwong834":[{"date":"2025-03-05","commitResults":[{"hash":"1032536f423f222b97ee64b5ede87c14195e79aa","isMergeCommit":false,"messageTitle":"Add photo to AboutUs","messageBody":"","fileTypesAndContributionMap":{"docs":{"insertions":3,"deletions":3}}}]},{"date":"2025-03-10","commitResults":[{"hash":"2bfe1d82c785363ac10107bc65f7b4b85f57e7fd","isMergeCommit":false,"messageTitle":"Update Glossary in DeveloperGuide","messageBody":"","fileTypesAndContributionMap":{"docs":{"insertions":5,"deletions":1}}}]},{"date":"2025-03-12","commitResults":[{"hash":"ddca9d9170270b2525a900e096c6a4bc005a2fe1","isMergeCommit":true,"messageTitle":"Merge pull request #32 from swatirajesh277/branch-update-readme","messageBody":"Update readme ","fileTypesAndContributionMap":{}}]}],"gekjunxu":[{"date":"2025-03-05","commitResults":[{"hash":"3ecddd0b08c6ec0be29feffb0261c919f5e72cf2","isMergeCommit":false,"messageTitle":"Update AboutUs","messageBody":"","fileTypesAndContributionMap":{"docs":{"insertions":3,"deletions":3}}}]},{"date":"2025-03-09","commitResults":[{"hash":"dbb081b6661142cbad9dc078c8c092c6d4c725e9","isMergeCommit":false,"messageTitle":"Update NFRs","messageBody":"","fileTypesAndContributionMap":{"docs":{"insertions":8,"deletions":1}}}]}],"swatirajesh277":[{"date":"2025-03-05","commitResults":[{"hash":"02e70241fc7b554eb2c9bc8b6deb385490337a2e","isMergeCommit":false,"messageTitle":"update about us page","messageBody":"","fileTypesAndContributionMap":{"docs":{"insertions":3,"deletions":3}}}]},{"date":"2025-03-09","commitResults":[{"hash":"a052efda9c21b3fe6269c3f666d19be2b3dfb679","isMergeCommit":false,"messageTitle":"Update readme to match project","messageBody":"","fileTypesAndContributionMap":{"docs":{"insertions":21,"deletions":9}}}]},{"date":"2025-03-12","commitResults":[{"hash":"21abdb377c34c23c44a4136081b1274b8ffde7ec","isMergeCommit":true,"messageTitle":"Merge pull request #34 from weiwong834/branch-Update-Glossary","messageBody":"Update Glossary","fileTypesAndContributionMap":{}},{"hash":"90d083cac701ef9e6536ee39d78cb0b1a3f5cdc1","isMergeCommit":true,"messageTitle":"Merge pull request #38 from ShiJianXi/Update-usecase","messageBody":"Update use case","fileTypesAndContributionMap":{}},{"hash":"124238421faa937c334effcbd9a9f5b1c65be32c","isMergeCommit":true,"messageTitle":"Merge pull request #36 from ShiJianXi/Update-userstories","messageBody":"Update user stories","fileTypesAndContributionMap":{}},{"hash":"2231d6e87962baedc177c47d9e48c07f2324f8e8","isMergeCommit":true,"messageTitle":"Merge pull request #31 from gekjunxu/add-NFRs","messageBody":"Update NFRs","fileTypesAndContributionMap":{}}]}],"ShiJianXi":[{"date":"2025-03-05","commitResults":[{"hash":"156d143b6f592e2f53e7b56f5ee2afb879441925","isMergeCommit":false,"messageTitle":"Update AboutUs by JianXi","messageBody":"","fileTypesAndContributionMap":{"docs":{"insertions":2,"deletions":2}}},{"hash":"25620e63d53f1711cbf46a52d1ef03c8dce36ce7","isMergeCommit":false,"messageTitle":"Update AboutUs JianXi","messageBody":"","fileTypesAndContributionMap":{"docs":{"insertions":1,"deletions":1}}},{"hash":"7fec064455461e5b4b6ba0fe7269ac668b289fdc","isMergeCommit":true,"messageTitle":"Merge pull request #25 from ShiJianXi/branch-UpdateAboutUs-JianXi","messageBody":"Update AboutUs JianXi","fileTypesAndContributionMap":{}}]},{"date":"2025-03-10","commitResults":[{"hash":"7362edccd7c31a801d933f43d860e3e3eda7ebaf","isMergeCommit":false,"messageTitle":"Update user stories","messageBody":"","fileTypesAndContributionMap":{"docs":{"insertions":35,"deletions":11}}},{"hash":"db66f29a166d72f25654bf3516d90cad3b2f4cec","isMergeCommit":false,"messageTitle":"Update use case","messageBody":"","fileTypesAndContributionMap":{"docs":{"insertions":37,"deletions":10}}}]}]},"authorFileTypeContributionMap":{"dragonesejosh":{"docs":5,"functional-code":0,"test-code":0},"weiwong834":{"docs":8,"functional-code":0,"test-code":0},"gekjunxu":{"docs":11,"functional-code":0,"test-code":0},"swatirajesh277":{"docs":23,"functional-code":0,"test-code":0},"ShiJianXi":{"docs":70,"functional-code":0,"test-code":0}},"authorContributionVariance":{"dragonesejosh":1.8399999,"weiwong834":3.2400005,"gekjunxu":5.2875,"swatirajesh277":43.56,"ShiJianXi":409.7475},"authorDisplayNameMap":{"dragonesejosh":"CS2103T-W12-3 JOSH..I EN","weiwong834":"CS2103T-W12-3 WONG.. YIN","gekjunxu":"CS2103T-W12-3 GEK ..N XU","swatirajesh277":"CS2103T-W12-3 RAJE..WATI","ShiJianXi":"CS2103T-W12-3 SHI ..ANXI"}}
