[{"path":"docs/AboutUs.md","fileType":"docs","lines":[{"lineNumber":1,"author":{"gitId":"-"},"content":"---","lastModifiedDate":"2020-05-23","isFullCredit":false},{"lineNumber":2,"author":{"gitId":"-"},"content":"  layout: default.md","lastModifiedDate":"2023-09-12","isFullCredit":false},{"lineNumber":3,"author":{"gitId":"-"},"content":"  title: \"About Us\"","lastModifiedDate":"2023-09-12","isFullCredit":false},{"lineNumber":4,"author":{"gitId":"-"},"content":"---","lastModifiedDate":"2020-05-23","isFullCredit":false},{"lineNumber":5,"author":{"gitId":"-"},"content":"","lastModifiedDate":"2020-05-23","isFullCredit":false},{"lineNumber":6,"author":{"gitId":"-"},"content":"# About Us","lastModifiedDate":"2023-09-12","isFullCredit":false},{"lineNumber":7,"author":{"gitId":"-"},"content":"","lastModifiedDate":"2023-09-12","isFullCredit":false},{"lineNumber":8,"author":{"gitId":"-"},"content":"We are a team based in the [School of Computing, National University of Singapore](http://www.comp.nus.edu.sg).","lastModifiedDate":"2023-09-12","isFullCredit":false},{"lineNumber":9,"author":{"gitId":"-"},"content":"","lastModifiedDate":"2020-05-23","isFullCredit":false},{"lineNumber":10,"author":{"gitId":"-"},"content":"You can reach us at the email `seer[at]comp.nus.edu.sg`","lastModifiedDate":"2020-06-17","isFullCredit":false},{"lineNumber":11,"author":{"gitId":"-"},"content":"","lastModifiedDate":"2020-06-17","isFullCredit":false},{"lineNumber":12,"author":{"gitId":"-"},"content":"## Project team","lastModifiedDate":"2020-06-07","isFullCredit":false},{"lineNumber":13,"author":{"gitId":"-"},"content":"","lastModifiedDate":"2020-05-23","isFullCredit":false},{"lineNumber":14,"author":{"gitId":"CXl0l0"},"content":"### Lee Chen Xuan","lastModifiedDate":"2025-03-06","isFullCredit":false},{"lineNumber":15,"author":{"gitId":"-"},"content":"","lastModifiedDate":"2020-05-23","isFullCredit":false},{"lineNumber":16,"author":{"gitId":"CXl0l0"},"content":"\u003cimg src\u003d\"images/cxl0l0.png\" width\u003d\"200px\"\u003e","lastModifiedDate":"2025-03-06","isFullCredit":false},{"lineNumber":17,"author":{"gitId":"-"},"content":"","lastModifiedDate":"2020-05-23","isFullCredit":false},{"lineNumber":18,"author":{"gitId":"CXl0l0"},"content":"[[github](https://github.com/CXl0l0)]","lastModifiedDate":"2025-03-06","isFullCredit":false},{"lineNumber":19,"author":{"gitId":"CXl0l0"},"content":"[[email](mailto:leechenxuan234@gmail.com)]","lastModifiedDate":"2025-03-06","isFullCredit":false},{"lineNumber":20,"author":{"gitId":"-"},"content":"","lastModifiedDate":"2020-05-23","isFullCredit":false},{"lineNumber":21,"author":{"gitId":"CXl0l0"},"content":"- Role: Developer","lastModifiedDate":"2025-03-06","isFullCredit":false},{"lineNumber":22,"author":{"gitId":"CXl0l0"},"content":"- Responsibilities: Proof-reading","lastModifiedDate":"2025-03-06","isFullCredit":false},{"lineNumber":23,"author":{"gitId":"-"},"content":"","lastModifiedDate":"2020-05-23","isFullCredit":false},{"lineNumber":24,"author":{"gitId":"zihung20"},"content":"### Kong Zi Hung","lastModifiedDate":"2025-03-06","isFullCredit":false},{"lineNumber":25,"author":{"gitId":"-"},"content":"","lastModifiedDate":"2020-05-23","isFullCredit":false},{"lineNumber":26,"author":{"gitId":"zihung20"},"content":"\u003cimg src\u003d\"images/zihung20.png\" width\u003d\"200px\"\u003e \u003cbr\u003e","lastModifiedDate":"2025-03-06","isFullCredit":false},{"lineNumber":27,"author":{"gitId":"-"},"content":"","lastModifiedDate":"2020-05-23","isFullCredit":false},{"lineNumber":28,"author":{"gitId":"zihung20"},"content":"Hi I am year 2 Computer Science student in NUS.","lastModifiedDate":"2025-03-06","isFullCredit":false},{"lineNumber":29,"author":{"gitId":"-"},"content":"","lastModifiedDate":"2020-05-23","isFullCredit":false},{"lineNumber":30,"author":{"gitId":"zihung20"},"content":"[[homepage](https://www.linkedin.com/in/kong-zi-hung-a32ab8288/)]","lastModifiedDate":"2025-03-06","isFullCredit":false},{"lineNumber":31,"author":{"gitId":"zihung20"},"content":"[[github](https://github.com/zihung20)]","lastModifiedDate":"2025-03-06","isFullCredit":false},{"lineNumber":32,"author":{"gitId":"zihung20"},"content":"[[email](mailto:zihung20@gmail.com)]","lastModifiedDate":"2025-03-06","isFullCredit":false},{"lineNumber":33,"author":{"gitId":"-"},"content":"","lastModifiedDate":"2020-05-23","isFullCredit":false},{"lineNumber":34,"author":{"gitId":"zihung20"},"content":"* Role: student","lastModifiedDate":"2025-03-06","isFullCredit":false},{"lineNumber":35,"author":{"gitId":"zihung20"},"content":"* Responsibilities: technical support, integration, documentation","lastModifiedDate":"2025-03-06","isFullCredit":false},{"lineNumber":36,"author":{"gitId":"-"},"content":"","lastModifiedDate":"2020-05-23","isFullCredit":false},{"lineNumber":37,"author":{"gitId":"Junixm"},"content":"### Jun Heng","lastModifiedDate":"2025-03-06","isFullCredit":false},{"lineNumber":38,"author":{"gitId":"-"},"content":"","lastModifiedDate":"2020-05-23","isFullCredit":false},{"lineNumber":39,"author":{"gitId":"Junixm"},"content":"\u003cimg src\u003d\"images/junixm.png\" width\u003d\"200px\"\u003e","lastModifiedDate":"2025-03-09","isFullCredit":false},{"lineNumber":40,"author":{"gitId":"-"},"content":"","lastModifiedDate":"2020-05-23","isFullCredit":false},{"lineNumber":41,"author":{"gitId":"Junixm"},"content":"[[github](http://github.com/junixm)]","lastModifiedDate":"2025-03-06","isFullCredit":false},{"lineNumber":42,"author":{"gitId":"Junixm"},"content":"[[portfolio](https://sites.google.com/view/leejunheng)]","lastModifiedDate":"2025-03-06","isFullCredit":false},{"lineNumber":43,"author":{"gitId":"-"},"content":"","lastModifiedDate":"2020-05-23","isFullCredit":false},{"lineNumber":44,"author":{"gitId":"-"},"content":"* Role: Developer","lastModifiedDate":"2020-05-23","isFullCredit":false},{"lineNumber":45,"author":{"gitId":"Junixm"},"content":"* Responsibilities: Deliverables and deadlines.","lastModifiedDate":"2025-03-06","isFullCredit":false},{"lineNumber":46,"author":{"gitId":"Junixm"},"content":"  Ensure project deliverables are done on time and in the right format.","lastModifiedDate":"2025-03-06","isFullCredit":false},{"lineNumber":47,"author":{"gitId":"-"},"content":"","lastModifiedDate":"2020-05-23","isFullCredit":false},{"lineNumber":48,"author":{"gitId":"CoreySiah"},"content":"### Corey Siah","lastModifiedDate":"2025-03-06","isFullCredit":false},{"lineNumber":49,"author":{"gitId":"-"},"content":"","lastModifiedDate":"2020-05-23","isFullCredit":false},{"lineNumber":50,"author":{"gitId":"CoreySiah"},"content":"\u003cimg src\u003d\"images/coreysiah.png\" width\u003d\"200px\"\u003e","lastModifiedDate":"2025-03-06","isFullCredit":false},{"lineNumber":51,"author":{"gitId":"-"},"content":"","lastModifiedDate":"2020-05-23","isFullCredit":false},{"lineNumber":52,"author":{"gitId":"CoreySiah"},"content":"[[github](http://github.com/coreysiah)]","lastModifiedDate":"2025-03-06","isFullCredit":false},{"lineNumber":53,"author":{"gitId":"-"},"content":"[[portfolio](team/johndoe.md)]","lastModifiedDate":"2020-05-23","isFullCredit":false},{"lineNumber":54,"author":{"gitId":"-"},"content":"","lastModifiedDate":"2020-05-23","isFullCredit":false},{"lineNumber":55,"author":{"gitId":"-"},"content":"* Role: Developer","lastModifiedDate":"2020-05-23","isFullCredit":false},{"lineNumber":56,"author":{"gitId":"CoreySiah"},"content":"* Responsibilities: User story and feature list","lastModifiedDate":"2025-03-06","isFullCredit":false}],"authorContributionMap":{"CXl0l0":6,"zihung20":8,"-":32,"Junixm":6,"CoreySiah":4}},{"path":"docs/team/johndoe.md","fileType":"docs","lines":[{"lineNumber":1,"author":{"gitId":"-"},"content":"---","lastModifiedDate":"2020-05-23","isFullCredit":false},{"lineNumber":2,"author":{"gitId":"-"},"content":"  layout: default.md","lastModifiedDate":"2023-09-12","isFullCredit":false},{"lineNumber":3,"author":{"gitId":"CoreySiah"},"content":"  title: \"Corey Portfolio Page\"","lastModifiedDate":"2025-03-06","isFullCredit":false},{"lineNumber":4,"author":{"gitId":"-"},"content":"---","lastModifiedDate":"2020-05-23","isFullCredit":false},{"lineNumber":5,"author":{"gitId":"-"},"content":"","lastModifiedDate":"2020-05-23","isFullCredit":false},{"lineNumber":6,"author":{"gitId":"CoreySiah"},"content":"### Project: HRQuickAccess","lastModifiedDate":"2025-03-06","isFullCredit":false},{"lineNumber":7,"author":{"gitId":"-"},"content":"","lastModifiedDate":"2020-05-23","isFullCredit":false},{"lineNumber":8,"author":{"gitId":"CoreySiah"},"content":"HRQuickAccess - A desktop address book application for quick, efficient access to troop details for streamlined communication and duty scheduling.","lastModifiedDate":"2025-03-06","isFullCredit":false},{"lineNumber":9,"author":{"gitId":"-"},"content":"","lastModifiedDate":"2020-05-23","isFullCredit":false},{"lineNumber":10,"author":{"gitId":"-"},"content":"Given below are my contributions to the project.","lastModifiedDate":"2020-05-23","isFullCredit":false},{"lineNumber":11,"author":{"gitId":"-"},"content":"","lastModifiedDate":"2020-05-23","isFullCredit":false},{"lineNumber":12,"author":{"gitId":"-"},"content":"* **Documentation**:","lastModifiedDate":"2020-05-23","isFullCredit":false},{"lineNumber":13,"author":{"gitId":"-"},"content":"  * User Guide:","lastModifiedDate":"2020-05-23","isFullCredit":false},{"lineNumber":14,"author":{"gitId":"CoreySiah"},"content":"    * Added documentation for the features `add`, `view`, `delete` and `assign`","lastModifiedDate":"2025-03-06","isFullCredit":false},{"lineNumber":15,"author":{"gitId":"CoreySiah"},"content":"    * Added target user profile hierarchy and rational","lastModifiedDate":"2025-03-06","isFullCredit":false}],"authorContributionMap":{"-":10,"CoreySiah":5}}]
